{
  "slides": [
    {
      "title": "Screen Time Before Bed",
      "image": "https://res.cloudinary.com/y59p8mph/image/upload/blog/screen-time-before-bed/hero.png",
      "body": "Why it makes bedtime harder — and what to do instead."
    },
    {
      "title": "Screens Keep Kids Awake",
      "image": "https://res.cloudinary.com/y59p8mph/image/upload/blog/screen-time-before-bed/blue-light.png",
      "body": "Blue light delays melatonin. Even 30 minutes before bed pushes sleep back and makes settling harder."
    },
    {
      "title": "Set a Screen-Off Time",
      "image": "https://res.cloudinary.com/y59p8mph/image/upload/blog/screen-time-before-bed/screen-off-time.png",
      "body": "Pick a fixed time — same every night. When kids know it's coming, they stop negotiating."
    },
    {
      "title": "Build a Wind-Down Routine",
      "image": "https://res.cloudinary.com/y59p8mph/image/upload/blog/screen-time-before-bed/wind-down.png",
      "body": "Bath, pajamas, teeth. The same order every night signals the brain that sleep is coming."
    },
    {
      "title": "Replace Screens With Calm",
      "image": "https://res.cloudinary.com/y59p8mph/image/upload/blog/screen-time-before-bed/bedtime-reading.png",
      "body": "Reading, drawing, quiet music. Give kids something that fills the same need — without the stimulation."
    },
    {
      "title": "Consistency Does the Work",
      "image": "https://res.cloudinary.com/y59p8mph/image/upload/blog/screen-time-before-bed/peaceful-bedroom.png",
      "body": "After a few weeks, most kids stop fighting bedtime entirely. The routine becomes what evenings simply look like."
    }
  ],
  "caption": "Screen time right before bed is making bedtime harder than it needs to be 😴\n\nHere's what's actually happening — and a simple routine that fixes it 👇\n\nSave this for tonight.\n\n#bedtimeroutine #screentimekids #kidsleep #parentingtips #bedtime"
}
